quartic_solver_kapoorlabs/__init__.py
quartic_solver_kapoorlabs/_version.py
quartic_solver_kapoorlabs/caped.yaml
quartic_solver_kapoorlabs/solvers.py
quartic_solver_kapoorlabs/_tests/__init__.py
quartic_solver_kapoorlabs/_tests/test_solve_quartic.py
quartic_solver_kapoorlabs-0.0.2.dist-info/LICENSE
quartic_solver_kapoorlabs-0.0.2.dist-info/METADATA
quartic_solver_kapoorlabs-0.0.2.dist-info/WHEEL
quartic_solver_kapoorlabs-0.0.2.dist-info/entry_points.txt
quartic_solver_kapoorlabs-0.0.2.dist-info/top_level.txt
quartic_solver_kapoorlabs-0.0.2.dist-info/RECORD
