Metadata-Version: 2.1
Name: quartic-solver-kapoorlabs
Version: 0.0.2
Summary: A package containing methods for solving quartic, cubic, quadratic, and depressed equations.
Home-page: https://github.com/Kapoorlabs-CAPED/quartic-solver
Author: Varun Kapoor
Author-email: randomaccessiblekapoor@gmail.com
License: BSD-3-Clause
Project-URL: Bug Tracker, https://github.com/Kapoorlabs-CAPED/quartic-solver/issues
Project-URL: Documentation, https://github.com/Kapoorlabs-CAPED/quartic-solver#README.md
Project-URL: Source Code, https://github.com/Kapoorlabs-CAPED/quartic-solver
Project-URL: User Support, https://github.com/Kapoorlabs-CAPED/quartic-solver/issues
Classifier: Development Status :: 5 - Production/Stable
Classifier: Intended Audience :: Developers
Classifier: License :: OSI Approved :: BSD License
Classifier: Operating System :: OS Independent
Classifier: Programming Language :: Python
Classifier: Programming Language :: Python :: 3
Classifier: Programming Language :: Python :: 3 :: Only
Classifier: Programming Language :: Python :: 3.8
Classifier: Programming Language :: Python :: 3.9
Classifier: Programming Language :: Python :: 3.10
Classifier: Topic :: Scientific/Engineering :: Image Processing
Requires-Python: >=3.8
License-File: LICENSE
Requires-Dist: caped-ai
Provides-Extra: testing
Requires-Dist: tox ; extra == 'testing'
Requires-Dist: pytest ; extra == 'testing'
Requires-Dist: pytest-cov ; extra == 'testing'
